jismeshcode/__init__.py
jismeshcode/jismeshcode.py
jismeshcode-0.1.8.dist-info/METADATA
jismeshcode-0.1.8.dist-info/WHEEL
jismeshcode-0.1.8.dist-info/RECORD
